aiocron/__init__.py
aiocron/__main__.py
aiocron-1.8.dist-info/LICENSE
aiocron-1.8.dist-info/METADATA
aiocron-1.8.dist-info/WHEEL
aiocron-1.8.dist-info/top_level.txt
aiocron-1.8.dist-info/RECORD
