Metadata-Version: 2.1
Name: aiocron
Version: 1.8
Summary: Crontabs for asyncio
Home-page: https://github.com/gawel/aiocron/
Author: Gael Pasgrimaud
Author-email: gael@gawel.org
License: MIT
Keywords: crontab cron asyncio
Platform: UNKNOWN
Classifier: Development Status :: 5 - Production/Stable
Classifier: Environment :: Web Environment
Classifier: Intended Audience :: Developers
Classifier: Operating System :: POSIX
Classifier: Programming Language :: Python :: 2.7
Classifier: Programming Language :: Python :: 3.4
Classifier: Programming Language :: Python :: 3.5
Classifier: Programming Language :: Python :: 3.6
Classifier: License :: OSI Approved :: MIT License
Classifier: Topic :: Software Development :: Libraries :: Python Modules
Provides-Extra: test
License-File: LICENSE
